keanu/__init__.py
keanu/__version__.py
keanu/base.py
keanu/context.py
keanu/description_creator.py
keanu/infer_type.py
keanu/java_exception.py
keanu/keanu_random.py
keanu/model.py
keanu/net.py
keanu/network_io.py
keanu/sequence.py
keanu/shape_validation.py
keanu/stats.py
keanu/tensor.py
keanu/vartypes.py
keanu/algorithm/__init__.py
keanu/algorithm/_proposal_distribution.py
keanu/algorithm/optimization.py
keanu/algorithm/proposal_listeners.py
keanu/algorithm/sampling.py
keanu/classpath/annotations-13.0.jar
keanu/classpath/commons-beanutils-1.9.3.jar
keanu/classpath/commons-collections-3.2.2.jar
keanu/classpath/commons-collections4-4.1.jar
keanu/classpath/commons-lang3-3.7.jar
keanu/classpath/commons-logging-1.2.jar
keanu/classpath/commons-math3-3.6.1.jar
keanu/classpath/commons-text-1.3.jar
keanu/classpath/joor-java-8-0.9.10.jar
keanu/classpath/keanu-0.0.26.jar
keanu/classpath/kotlin-stdlib-1.2.31.jar
keanu/classpath/kotlin-stdlib-jdk7-1.2.31.jar
keanu/classpath/kotlin-stdlib-jdk8-1.2.31.jar
keanu/classpath/log4j-1.2.17.jar
keanu/classpath/opencsv-4.2.jar
keanu/classpath/protobuf-java-3.6.1.jar
keanu/classpath/protobuf-java-util-3.6.1.jar
keanu/classpath/slf4j-api-1.8.0-beta2.jar
keanu/classpath/slf4j-log4j12-1.8.0-beta2.jar
keanu/functional/__init__.py
keanu/functional/biconsumer.py
keanu/functional/consumer.py
keanu/functional/function.py
keanu/functional/hash_shortener.py
keanu/functional/iterator.py
keanu/functional/supplier.py
keanu/plots/__init__.py
keanu/plots/autocorrelation.py
keanu/plots/traceplot.py
keanu/vertex/__init__.py
keanu/vertex/base.py
keanu/vertex/const.py
keanu/vertex/generated.py
keanu/vertex/iff.py
keanu/vertex/label.py
keanu/vertex/lambda_model.py
keanu/vertex/vertex_casting.py
keanu-0.0.26.dev1.dist-info/LICENSE
keanu-0.0.26.dev1.dist-info/METADATA
keanu-0.0.26.dev1.dist-info/WHEEL
keanu-0.0.26.dev1.dist-info/top_level.txt
keanu-0.0.26.dev1.dist-info/RECORD
