Metadata-Version: 2.1
Name: keanu
Version: 0.0.26.dev1
Summary: A probabilistic approach from an Improbabilistic company
Home-page: https://improbable-research.github.io/keanu/python
Author: Improbable Worlds
Author-email: keanu-engineering@improbable.io
License: MIT
Platform: UNKNOWN
Classifier: Development Status :: 1 - Planning
Classifier: License :: OSI Approved :: MIT License
Classifier: Programming Language :: Python :: 3.6
Requires-Dist: py4j
Requires-Dist: numpy
Requires-Dist: pandas
Requires-Dist: nd4j (==1.0.0-beta3)
